{
    "auth": {
        "employees1bae417f": {
            "service": "Cognito",
            "providerPlugin": "awscloudformation",
            "dependsOn": [],
            "customAuth": false,
            "frontendAuthConfig": {
                "socialProviders": [],
                "usernameAttributes": [],
                "signupAttributes": [
                    "EMAIL"
                ],
                "passwordProtectionSettings": {
                    "passwordPolicyMinLength": 8,
                    "passwordPolicyCharacters": []
                },
                "mfaConfiguration": "OFF",
                "mfaTypes": [
                    "SMS"
                ],
                "verificationMechanisms": [
                    "EMAIL"
                ]
            }
        }
    },
    "storage": {
        "employeesdb": {
            "service": "DynamoDB",
            "providerPlugin": "awscloudformation"
        }
    },
    "function": {
        "employeesfunction": {
            "build": true,
            "providerPlugin": "awscloudformation",
            "service": "Lambda",
            "dependsOn": [
                {
                    "category": "storage",
                    "resourceName": "employeesdb",
                    "attributes": [
                        "Name",
                        "Arn"
                    ],
                    "attributeEnvMap": {
                        "Name": "TABLE_NAME",
                        "Arn": "TABLE_ARN"
                    }
                }
            ]
        }
    },
    "api": {
        "employeesapi": {
            "service": "API Gateway",
            "providerPlugin": "awscloudformation",
            "dependsOn": [
                {
                    "category": "function",
                    "resourceName": "employeesfunction",
                    "attributes": [
                        "Name",
                        "Arn"
                    ]
                }
            ]
        }
    },
    "hosting": {
        "amplifyhosting": {
            "service": "amplifyhosting",
            "type": "cicd"
        }
    }
}